thermopot/__init__.py
thermopot/calculations.py
thermopot/interpolate.py
thermopot/materials.py
thermopot/potential.py
thermopot/potentials.py
thermopot/reactions.py
thermopot-1.1.1.dist-info/METADATA
thermopot-1.1.1.dist-info/WHEEL
thermopot-1.1.1.dist-info/top_level.txt
thermopot-1.1.1.dist-info/RECORD
