Metadata-Version: 2.1
Name: thermopot
Version: 1.1.1
Summary: Software for ab-initio thermodynamic modelling of material formation and decomposition.
Home-page: https://github.com/NU-CEM/ThermoPot
Author: NU-CEM
Author-email: l.whalley@northumbria.ac.uk
Project-URL: Bug Tracker, https://github.com/NU-CEM/ThermoPot/issues
Keywords: materials science,physics,chemistry
Classifier: Development Status :: 4 - Beta
Classifier: Intended Audience :: Science/Research
Classifier: Programming Language :: Python :: 3
Classifier: Topic :: Scientific/Engineering
Classifier: License :: OSI Approved :: GNU General Public License v3 (GPLv3)
Classifier: Operating System :: OS Independent
Requires-Dist: matplotlib
Requires-Dist: numpy
Requires-Dist: scipy
Provides-Extra: dev
Requires-Dist: black ; extra == 'dev'
Provides-Extra: tests
Requires-Dist: pytest ; extra == 'tests'
